[
  {
    "__type__": "cc.Prefab",
    "_name": "ChallengeCell",
    "_objFlags": 0,
    "_rawFiles": null,
    "data": {
      "__id__": 1
    },
    "asyncLoadAssets": false
  },
  {
    "__type__": "cc.Node",
    "_name": "ChallengeCell",
    "_objFlags": 0,
    "_parent": null,
    "_children": [
      {
        "__id__": 2
      },
      {
        "__id__": 6
      },
      {
        "__id__": 9
      },
      {
        "__id__": 12
      },
      {
        "__id__": 15
      },
      {
        "__id__": 18
      },
      {
        "__id__": 21
      },
      {
        "__id__": 24
      }
    ],
    "_tag": -1,
    "_active": true,
    "_components": [
      {
        "__id__": 29
      }
    ],
    "_prefab": {
      "__id__": 30
    },
    "_id": "",
    "_opacity": 255,
    "_color": {
      "__type__": "cc.Color",
      "r": 255,
      "g": 255,
      "b": 255,
      "a": 255
    },
    "_cascadeOpacityEnabled": true,
    "_anchorPoint": {
      "__type__": "cc.Vec2",
      "x": 0.5,
      "y": 0.5
    },
    "_contentSize": {
      "__type__": "cc.Size",
      "width": 900,
      "height": 135
    },
    "_rotationX": 0,
    "_rotationY": 0,
    "_scaleX": 1,
    "_scaleY": 1,
    "_position": {
      "__type__": "cc.Vec2",
      "x": 0,
      "y": -345
    },
    "_skewX": 0,
    "_skewY": 0,
    "_localZOrder": 0,
    "_globalZOrder": 0,
    "_opacityModifyRGB": false,
    "groupIndex": 0
  },
  {
    "__type__": "cc.Node",
    "_name": "sprBg",
    "_objFlags": 0,
    "_parent": {
      "__id__": 1
    },
    "_children": [],
    "_tag": -1,
    "_active": true,
    "_components": [
      {
        "__id__": 3
      },
      {
        "__id__": 4
      }
    ],
    "_prefab": {
      "__id__": 5
    },
    "_id": "",
    "_opacity": 255,
    "_color": {
      "__type__": "cc.Color",
      "r": 251,
      "g": 224,
      "b": 153,
      "a": 255
    },
    "_cascadeOpacityEnabled": true,
    "_anchorPoint": {
      "__type__": "cc.Vec2",
      "x": 0.5,
      "y": 0.5
    },
    "_contentSize": {
      "__type__": "cc.Size",
      "width": 900,
      "height": 135
    },
    "_rotationX": 0,
    "_rotationY": 0,
    "_scaleX": 1,
    "_scaleY": 1,
    "_position": {
      "__type__": "cc.Vec2",
      "x": 0,
      "y": 0
    },
    "_skewX": 0,
    "_skewY": 0,
    "_localZOrder": 0,
    "_globalZOrder": 0,
    "_opacityModifyRGB": false,
    "groupIndex": 0
  },
  {
    "__type__": "cc.Sprite",
    "_name": "",
    "_objFlags": 0,
    "node": {
      "__id__": 2
    },
    "_enabled": true,
    "_spriteFrame": {
      "__uuid__": "44e075f5-ad8a-4766-97ba-0c07f1e29e0d"
    },
    "_type": 1,
    "_sizeMode": 0,
    "_fillType": 0,
    "_fillCenter": {
      "__type__": "cc.Vec2",
      "x": 0,
      "y": 0
    },
    "_fillStart": 0,
    "_fillRange": 0,
    "_isTrimmedMode": true,
    "_srcBlendFactor": 770,
    "_dstBlendFactor": 771,
    "_atlas": null
  },
  {
    "__type__": "cc.Widget",
    "_name": "",
    "_objFlags": 0,
    "node": {
      "__id__": 2
    },
    "_enabled": true,
    "isAlignOnce": true,
    "_target": null,
    "_alignFlags": 45,
    "_left": 0,
    "_right": 0,
    "_top": 0,
    "_bottom": 0,
    "_verticalCenter": 0,
    "_horizontalCenter": 0,
    "_isAbsLeft": true,
    "_isAbsRight": true,
    "_isAbsTop": true,
    "_isAbsBottom": true,
    "_isAbsHorizontalCenter": true,
    "_isAbsVerticalCenter": true,
    "_originalWidth": 100,
    "_originalHeight": 100
  },
  {
    "__type__": "cc.PrefabInfo",
    "root": {
      "__id__": 1
    },
    "asset": {
      "__uuid__": "d4969d64-db57-49fd-ae3a-423886d9bea1"
    },
    "fileId": "20xktBMahEE6tyhSuP4j6f",
    "sync": false
  },
  {
    "__type__": "cc.Node",
    "_name": "sprHead_my",
    "_objFlags": 0,
    "_parent": {
      "__id__": 1
    },
    "_children": [],
    "_tag": -1,
    "_active": true,
    "_components": [
      {
        "__id__": 7
      }
    ],
    "_prefab": {
      "__id__": 8
    },
    "_id": "",
    "_opacity": 255,
    "_color": {
      "__type__": "cc.Color",
      "r": 255,
      "g": 255,
      "b": 255,
      "a": 255
    },
    "_cascadeOpacityEnabled": true,
    "_anchorPoint": {
      "__type__": "cc.Vec2",
      "x": 0.5,
      "y": 0.5
    },
    "_contentSize": {
      "__type__": "cc.Size",
      "width": 90,
      "height": 90
    },
    "_rotationX": 0,
    "_rotationY": 0,
    "_scaleX": 1,
    "_scaleY": 1,
    "_position": {
      "__type__": "cc.Vec2",
      "x": -250,
      "y": 0
    },
    "_skewX": 0,
    "_skewY": 0,
    "_localZOrder": 0,
    "_globalZOrder": 0,
    "_opacityModifyRGB": false,
    "groupIndex": 0
  },
  {
    "__type__": "cc.Sprite",
    "_name": "",
    "_objFlags": 0,
    "node": {
      "__id__": 6
    },
    "_enabled": true,
    "_spriteFrame": {
      "__uuid__": "8cdb44ac-a3f6-449f-b354-7cd48cf84061"
    },
    "_type": 0,
    "_sizeMode": 0,
    "_fillType": 0,
    "_fillCenter": {
      "__type__": "cc.Vec2",
      "x": 0,
      "y": 0
    },
    "_fillStart": 0,
    "_fillRange": 0,
    "_isTrimmedMode": true,
    "_srcBlendFactor": 770,
    "_dstBlendFactor": 771,
    "_atlas": null
  },
  {
    "__type__": "cc.PrefabInfo",
    "root": {
      "__id__": 1
    },
    "asset": {
      "__uuid__": "d4969d64-db57-49fd-ae3a-423886d9bea1"
    },
    "fileId": "a2QD+giwhNm4oa3nkmJ9Bh",
    "sync": false
  },
  {
    "__type__": "cc.Node",
    "_name": "lbScore_my",
    "_objFlags": 0,
    "_parent": {
      "__id__": 1
    },
    "_children": [],
    "_tag": -1,
    "_active": true,
    "_components": [
      {
        "__id__": 10
      }
    ],
    "_prefab": {
      "__id__": 11
    },
    "_id": "",
    "_opacity": 255,
    "_color": {
      "__type__": "cc.Color",
      "r": 172,
      "g": 74,
      "b": 3,
      "a": 255
    },
    "_cascadeOpacityEnabled": true,
    "_anchorPoint": {
      "__type__": "cc.Vec2",
      "x": 0.5,
      "y": 0.5
    },
    "_contentSize": {
      "__type__": "cc.Size",
      "width": 89,
      "height": 40
    },
    "_rotationX": 0,
    "_rotationY": 0,
    "_scaleX": 1,
    "_scaleY": 1,
    "_position": {
      "__type__": "cc.Vec2",
      "x": -145,
      "y": 0
    },
    "_skewX": 0,
    "_skewY": 0,
    "_localZOrder": 0,
    "_globalZOrder": 0,
    "_opacityModifyRGB": false,
    "groupIndex": 0
  },
  {
    "__type__": "cc.Label",
    "_name": "",
    "_objFlags": 0,
    "node": {
      "__id__": 9
    },
    "_enabled": true,
    "_useOriginalSize": false,
    "_actualFontSize": 40,
    "_fontSize": 40,
    "_lineHeight": 40,
    "_enableWrapText": true,
    "_N$file": null,
    "_isSystemFontUsed": true,
    "_spacingX": 0,
    "_N$string": "9999",
    "_N$horizontalAlign": 1,
    "_N$verticalAlign": 1,
    "_N$fontFamily": "Arial",
    "_N$overflow": 0
  },
  {
    "__type__": "cc.PrefabInfo",
    "root": {
      "__id__": 1
    },
    "asset": {
      "__uuid__": "d4969d64-db57-49fd-ae3a-423886d9bea1"
    },
    "fileId": "6bwjWumspESK3Y0GxOTfR7",
    "sync": false
  },
  {
    "__type__": "cc.Node",
    "_name": "lbDate",
    "_objFlags": 0,
    "_parent": {
      "__id__": 1
    },
    "_children": [],
    "_tag": -1,
    "_active": true,
    "_components": [
      {
        "__id__": 13
      }
    ],
    "_prefab": {
      "__id__": 14
    },
    "_id": "",
    "_opacity": 255,
    "_color": {
      "__type__": "cc.Color",
      "r": 172,
      "g": 74,
      "b": 3,
      "a": 255
    },
    "_cascadeOpacityEnabled": true,
    "_anchorPoint": {
      "__type__": "cc.Vec2",
      "x": 0.5,
      "y": 0.5
    },
    "_contentSize": {
      "__type__": "cc.Size",
      "width": 102,
      "height": 40
    },
    "_rotationX": 0,
    "_rotationY": 0,
    "_scaleX": 1,
    "_scaleY": 1,
    "_position": {
      "__type__": "cc.Vec2",
      "x": 0,
      "y": 0
    },
    "_skewX": 0,
    "_skewY": 0,
    "_localZOrder": 0,
    "_globalZOrder": 0,
    "_opacityModifyRGB": false,
    "groupIndex": 0
  },
  {
    "__type__": "cc.Label",
    "_name": "",
    "_objFlags": 0,
    "node": {
      "__id__": 12
    },
    "_enabled": true,
    "_useOriginalSize": false,
    "_actualFontSize": 40,
    "_fontSize": 40,
    "_lineHeight": 40,
    "_enableWrapText": true,
    "_N$file": null,
    "_isSystemFontUsed": true,
    "_spacingX": 0,
    "_N$string": "05-20",
    "_N$horizontalAlign": 1,
    "_N$verticalAlign": 1,
    "_N$fontFamily": "Arial",
    "_N$overflow": 0
  },
  {
    "__type__": "cc.PrefabInfo",
    "root": {
      "__id__": 1
    },
    "asset": {
      "__uuid__": "d4969d64-db57-49fd-ae3a-423886d9bea1"
    },
    "fileId": "48e2TqGyhBjoA/NK5XrRTR",
    "sync": false
  },
  {
    "__type__": "cc.Node",
    "_name": "sprHead_challenge",
    "_objFlags": 0,
    "_parent": {
      "__id__": 1
    },
    "_children": [],
    "_tag": -1,
    "_active": true,
    "_components": [
      {
        "__id__": 16
      }
    ],
    "_prefab": {
      "__id__": 17
    },
    "_id": "",
    "_opacity": 255,
    "_color": {
      "__type__": "cc.Color",
      "r": 255,
      "g": 255,
      "b": 255,
      "a": 255
    },
    "_cascadeOpacityEnabled": true,
    "_anchorPoint": {
      "__type__": "cc.Vec2",
      "x": 0.5,
      "y": 0.5
    },
    "_contentSize": {
      "__type__": "cc.Size",
      "width": 90,
      "height": 90
    },
    "_rotationX": 0,
    "_rotationY": 0,
    "_scaleX": 1,
    "_scaleY": 1,
    "_position": {
      "__type__": "cc.Vec2",
      "x": 250,
      "y": 0
    },
    "_skewX": 0,
    "_skewY": 0,
    "_localZOrder": 0,
    "_globalZOrder": 0,
    "_opacityModifyRGB": false,
    "groupIndex": 0
  },
  {
    "__type__": "cc.Sprite",
    "_name": "",
    "_objFlags": 0,
    "node": {
      "__id__": 15
    },
    "_enabled": true,
    "_spriteFrame": {
      "__uuid__": "8cdb44ac-a3f6-449f-b354-7cd48cf84061"
    },
    "_type": 0,
    "_sizeMode": 0,
    "_fillType": 0,
    "_fillCenter": {
      "__type__": "cc.Vec2",
      "x": 0,
      "y": 0
    },
    "_fillStart": 0,
    "_fillRange": 0,
    "_isTrimmedMode": true,
    "_srcBlendFactor": 770,
    "_dstBlendFactor": 771,
    "_atlas": null
  },
  {
    "__type__": "cc.PrefabInfo",
    "root": {
      "__id__": 1
    },
    "asset": {
      "__uuid__": "d4969d64-db57-49fd-ae3a-423886d9bea1"
    },
    "fileId": "08Ow3lco5N0qrpps+qTzjT",
    "sync": false
  },
  {
    "__type__": "cc.Node",
    "_name": "lbScore_challenge",
    "_objFlags": 0,
    "_parent": {
      "__id__": 1
    },
    "_children": [],
    "_tag": -1,
    "_active": true,
    "_components": [
      {
        "__id__": 19
      }
    ],
    "_prefab": {
      "__id__": 20
    },
    "_id": "",
    "_opacity": 255,
    "_color": {
      "__type__": "cc.Color",
      "r": 172,
      "g": 74,
      "b": 3,
      "a": 255
    },
    "_cascadeOpacityEnabled": true,
    "_anchorPoint": {
      "__type__": "cc.Vec2",
      "x": 0.5,
      "y": 0.5
    },
    "_contentSize": {
      "__type__": "cc.Size",
      "width": 89,
      "height": 40
    },
    "_rotationX": 0,
    "_rotationY": 0,
    "_scaleX": 1,
    "_scaleY": 1,
    "_position": {
      "__type__": "cc.Vec2",
      "x": 145,
      "y": 0
    },
    "_skewX": 0,
    "_skewY": 0,
    "_localZOrder": 0,
    "_globalZOrder": 0,
    "_opacityModifyRGB": false,
    "groupIndex": 0
  },
  {
    "__type__": "cc.Label",
    "_name": "",
    "_objFlags": 0,
    "node": {
      "__id__": 18
    },
    "_enabled": true,
    "_useOriginalSize": false,
    "_actualFontSize": 40,
    "_fontSize": 40,
    "_lineHeight": 40,
    "_enableWrapText": true,
    "_N$file": null,
    "_isSystemFontUsed": true,
    "_spacingX": 0,
    "_N$string": "9999",
    "_N$horizontalAlign": 1,
    "_N$verticalAlign": 1,
    "_N$fontFamily": "Arial",
    "_N$overflow": 0
  },
  {
    "__type__": "cc.PrefabInfo",
    "root": {
      "__id__": 1
    },
    "asset": {
      "__uuid__": "d4969d64-db57-49fd-ae3a-423886d9bea1"
    },
    "fileId": "9fldLLXAxHl5lvccnKf6ZJ",
    "sync": false
  },
  {
    "__type__": "cc.Node",
    "_name": "challengeFlag",
    "_objFlags": 0,
    "_parent": {
      "__id__": 1
    },
    "_children": [],
    "_tag": -1,
    "_active": true,
    "_components": [
      {
        "__id__": 22
      }
    ],
    "_prefab": {
      "__id__": 23
    },
    "_id": "",
    "_opacity": 255,
    "_color": {
      "__type__": "cc.Color",
      "r": 255,
      "g": 255,
      "b": 255,
      "a": 255
    },
    "_cascadeOpacityEnabled": true,
    "_anchorPoint": {
      "__type__": "cc.Vec2",
      "x": 0.5,
      "y": 0.5
    },
    "_contentSize": {
      "__type__": "cc.Size",
      "width": 133,
      "height": 105
    },
    "_rotationX": 0,
    "_rotationY": 0,
    "_scaleX": 1,
    "_scaleY": 1,
    "_position": {
      "__type__": "cc.Vec2",
      "x": -375,
      "y": 0
    },
    "_skewX": 0,
    "_skewY": 0,
    "_localZOrder": 0,
    "_globalZOrder": 0,
    "_opacityModifyRGB": false,
    "groupIndex": 0
  },
  {
    "__type__": "cc.Sprite",
    "_name": "",
    "_objFlags": 0,
    "node": {
      "__id__": 21
    },
    "_enabled": true,
    "_spriteFrame": {
      "__uuid__": "824ed591-1b76-4e3a-9383-d8b2c3b508ca"
    },
    "_type": 0,
    "_sizeMode": 1,
    "_fillType": 0,
    "_fillCenter": {
      "__type__": "cc.Vec2",
      "x": 0,
      "y": 0
    },
    "_fillStart": 0,
    "_fillRange": 0,
    "_isTrimmedMode": true,
    "_srcBlendFactor": 770,
    "_dstBlendFactor": 771,
    "_atlas": null
  },
  {
    "__type__": "cc.PrefabInfo",
    "root": {
      "__id__": 1
    },
    "asset": {
      "__uuid__": "d4969d64-db57-49fd-ae3a-423886d9bea1"
    },
    "fileId": "f5dBzfV4FOVYruaJlTNdA5",
    "sync": false
  },
  {
    "__type__": "cc.Node",
    "_name": "btn_challenge",
    "_objFlags": 0,
    "_parent": {
      "__id__": 1
    },
    "_children": [],
    "_tag": -1,
    "_active": true,
    "_components": [
      {
        "__id__": 25
      },
      {
        "__id__": 26
      }
    ],
    "_prefab": {
      "__id__": 28
    },
    "_id": "",
    "_opacity": 255,
    "_color": {
      "__type__": "cc.Color",
      "r": 255,
      "g": 255,
      "b": 255,
      "a": 255
    },
    "_cascadeOpacityEnabled": true,
    "_anchorPoint": {
      "__type__": "cc.Vec2",
      "x": 0.5,
      "y": 0.5
    },
    "_contentSize": {
      "__type__": "cc.Size",
      "width": 130,
      "height": 88
    },
    "_rotationX": 0,
    "_rotationY": 0,
    "_scaleX": 1,
    "_scaleY": 1,
    "_position": {
      "__type__": "cc.Vec2",
      "x": 371,
      "y": 0
    },
    "_skewX": 0,
    "_skewY": 0,
    "_localZOrder": 0,
    "_globalZOrder": 0,
    "_opacityModifyRGB": false,
    "groupIndex": 0
  },
  {
    "__type__": "cc.Sprite",
    "_name": "",
    "_objFlags": 0,
    "node": {
      "__id__": 24
    },
    "_enabled": true,
    "_spriteFrame": {
      "__uuid__": "5c945486-3e5c-4ee6-a2e6-a80089ad42c3"
    },
    "_type": 0,
    "_sizeMode": 1,
    "_fillType": 0,
    "_fillCenter": {
      "__type__": "cc.Vec2",
      "x": 0,
      "y": 0
    },
    "_fillStart": 0,
    "_fillRange": 0,
    "_isTrimmedMode": true,
    "_srcBlendFactor": 770,
    "_dstBlendFactor": 771,
    "_atlas": null
  },
  {
    "__type__": "cc.Button",
    "_name": "",
    "_objFlags": 0,
    "node": {
      "__id__": 24
    },
    "_enabled": true,
    "transition": 0,
    "pressedColor": {
      "__type__": "cc.Color",
      "r": 211,
      "g": 211,
      "b": 211,
      "a": 255
    },
    "hoverColor": {
      "__type__": "cc.Color",
      "r": 255,
      "g": 255,
      "b": 255,
      "a": 255
    },
    "duration": 0.1,
    "zoomScale": 1.2,
    "clickEvents": [
      {
        "__id__": 27
      }
    ],
    "_N$interactable": true,
    "_N$enableAutoGrayEffect": false,
    "_N$normalColor": {
      "__type__": "cc.Color",
      "r": 214,
      "g": 214,
      "b": 214,
      "a": 255
    },
    "_N$disabledColor": {
      "__type__": "cc.Color",
      "r": 124,
      "g": 124,
      "b": 124,
      "a": 255
    },
    "_N$normalSprite": null,
    "_N$pressedSprite": null,
    "pressedSprite": null,
    "_N$hoverSprite": null,
    "hoverSprite": null,
    "_N$disabledSprite": null,
    "_N$target": {
      "__id__": 24
    }
  },
  {
    "__type__": "cc.ClickEvent",
    "target": {
      "__id__": 1
    },
    "component": "ChallengeCell",
    "handler": "btnChallenge",
    "customEventData": ""
  },
  {
    "__type__": "cc.PrefabInfo",
    "root": {
      "__id__": 1
    },
    "asset": {
      "__uuid__": "d4969d64-db57-49fd-ae3a-423886d9bea1"
    },
    "fileId": "63p4eJ8lNEXqWL/+ETNayx",
    "sync": false
  },
  {
    "__type__": "0ab8frROmhO6bjoHp+b7KK3",
    "_name": "",
    "_objFlags": 0,
    "node": {
      "__id__": 1
    },
    "_enabled": true,
    "sprHead_my": {
      "__id__": 7
    },
    "lbScore_my": {
      "__id__": 10
    },
    "sprHead_challenge": {
      "__id__": 16
    },
    "lbScore_challenge": {
      "__id__": 19
    },
    "lbDate": {
      "__id__": 13
    },
    "challengeFlag": {
      "__id__": 22
    },
    "btn_challenge": {
      "__id__": 24
    },
    "challengeFlagFrames": [
      {
        "__uuid__": "5952265a-2702-4c5e-99bd-eb1b1e1b01c8"
      },
      {
        "__uuid__": "824ed591-1b76-4e3a-9383-d8b2c3b508ca"
      }
    ]
  },
  {
    "__type__": "cc.PrefabInfo",
    "root": {
      "__id__": 1
    },
    "asset": {
      "__uuid__": "d4969d64-db57-49fd-ae3a-423886d9bea1"
    },
    "fileId": "ddUpHfWvFI1ILDQk3uV1hZ",
    "sync": false
  }
]